{
  "sources": [
    {
      "type": "category",
      "id": "Lingerie-83",
      "tag": "內衣絲襪",
      "sort": "uploaddate",
      "pages": 5
    },
    {
      "type": "search",
      "id": "日本",
      "keyword": "日本",
      "tag": "日本",
      "sort": "uploaddate",
      "pages": 5
    },
    {
      "type": "search",
      "id": "中國",
      "keyword": "中國",
      "tag": "中國",
      "sort": "uploaddate",
      "pages": 5
    },
    {
      "type": "category",
      "id": "Creampie-40",
      "tag": "內射",
      "sort": "uploaddate",
      "pages": 5
    },
    {
      "type": "user",
      "id": "maderotic",
      "tag": "maderotic",
      "sort": "uploaddate",
      "pages": 5
    }
  ]
}
